{"nodes":[{"id":"GE","position":{"x":419.74969916464363,"y":-44.8346534747366},"data":{"id":"GE","nodeType":"countryNode","country":{"flags":{"png":"https://flagcdn.com/w320/ge.png","svg":"https://flagcdn.com/ge.svg","alt":"The flag of Georgia has a white field with a large centered red cross that extends to the edges and divides the field into four quarters. A small red Bolnur-Katskhuri cross is centered in each quarter."},"name":{"common":"Georgia","official":"Georgia","nativeName":{"kat":{"official":"საქართველო","common":"საქართველო"}}},"cca2":"GE"}},"type":"countryNode","measured":{"width":144,"height":52},"selected":false,"dragging":false},{"id":"GS","position":{"x":72.63536556667631,"y":937.9114356656311},"data":{"id":"GS","nodeType":"countryNode","country":{"flags":{"png":"https://flagcdn.com/w320/gs.png","svg":"https://flagcdn.com/gs.svg","alt":""},"name":{"common":"South Georgia","official":"South Georgia and the South Sandwich Islands","nativeName":{"eng":{"official":"South Georgia and the South Sandwich Islands","common":"South Georgia"}}},"cca2":"GS"}},"type":"countryNode","measured":{"width":354,"height":52},"selected":false,"dragging":false},{"id":"aa9db8b1-18b8-4dd4-8975-45f90a0a5a75","position":{"x":88.67261613839293,"y":137.19442497778138},"data":{"nodeType":"hotelNode","nodeUniqueData":{"hotelName":"Cool Hotel","starsAmount":4,"nightsSpent":5}},"type":"hotelNode","measured":{"width":218,"height":194},"selected":false,"dragging":false},{"id":"30617d7b-7dbe-4260-8f1d-eafb71d4a48b","position":{"x":389.9438233070688,"y":154.3771934474778},"data":{"nodeType":"bbqNode","nodeUniqueData":{"airportName":"Cool Barbeque Place","bbqType":"Marshmallows","taste":"Very good"}},"type":"bbqNode","measured":{"width":218,"height":172},"selected":false,"dragging":false},{"id":"1cca4fe6-57d9-488a-b4dc-aa6761a4b840","position":{"x":255.91822924343717,"y":421.28286367676105},"data":{"nodeType":"beachNode","nodeUniqueData":{"beachName":"Cool Beach","beachType":"Surfing","waterDepth":"Very deep"}},"type":"beachNode","measured":{"width":218,"height":198},"selected":false,"dragging":false},{"id":"aafcf9c6-2251-4398-a5ec-50a61dadbb7a","position":{"x":486.1673267373683,"y":679.0243907222062},"data":{"nodeType":"portNode","nodeUniqueData":{"airportName":"Cool Port","shipType":"Cruise","dinnerAt":"9:00 PM"}},"type":"portNode","measured":{"width":218,"height":176},"selected":false,"dragging":false},{"id":"d12732ba-834c-4aa4-b0fb-6ae0922358e6","position":{"x":27.399045621451883,"y":1198.238164397001},"data":{"nodeType":"bbqNode","nodeUniqueData":{"airportName":"Cool Barbeque Place","bbqType":"Marshmallows","taste":"Very good"}},"type":"bbqNode","measured":{"width":218,"height":172}},{"id":"23779701-3d5b-4157-886b-643f1f1dd1e1","position":{"x":317.50283738125614,"y":1165.5303839534936},"data":{"nodeType":"beachNode","nodeUniqueData":{"beachName":"Cool Beach","beachType":"Surfing","waterDepth":"Very deep"}},"type":"beachNode","measured":{"width":218,"height":198}},{"id":"bf38712d-1114-4b03-b926-5b0fe36d66e9","position":{"x":698.6195834186461,"y":1172.6407710064298},"data":{"nodeType":"trainNode","nodeUniqueData":{"stationName":"Cool Train Station","trainType":"Steam Locomotive","vibeCheck":"Very Cool Train"}},"type":"trainNode","measured":{"width":242,"height":198},"selected":false,"dragging":false},{"id":"DK","position":{"x":378.1520478821699,"y":1506.3096886171802},"data":{"id":"DK","nodeType":"countryNode","country":{"flags":{"png":"https://flagcdn.com/w320/dk.png","svg":"https://flagcdn.com/dk.svg","alt":"The flag of Denmark has a red field with a large white cross that extend to the edges of the field. The vertical part of this cross is offset towards the hoist side."},"name":{"common":"Denmark","official":"Kingdom of Denmark","nativeName":{"dan":{"official":"Kongeriget Danmark","common":"Danmark"}}},"cca2":"DK"}},"type":"countryNode","measured":{"width":246,"height":52},"selected":false,"dragging":false},{"id":"46e7aa33-2b96-4bf8-9c72-f4f5295b2e0f","position":{"x":-25.09795211783012,"y":1672.3096886171802},"data":{"nodeType":"airportNode","nodeUniqueData":{"airportName":"Cool Airport","flightTime":"4:00 AM"}},"type":"airportNode","measured":{"width":218,"height":158},"selected":false,"dragging":false},{"id":"0ffce9f9-640f-4114-badd-0dbb99e9d939","position":{"x":326.9020478821699,"y":1644.3096886171802},"data":{"nodeType":"bbqNode","nodeUniqueData":{"airportName":"Cool Barbeque Place","bbqType":"Marshmallows","taste":"Very good"}},"type":"bbqNode","measured":{"width":218,"height":172},"selected":false,"dragging":false},{"id":"b19cd9c6-ec33-439b-95d0-3a6f6c3811aa","position":{"x":118.90204788216988,"y":1956.3096886171802},"data":{"nodeType":"trainNode","nodeUniqueData":{"stationName":"Cool Train Station","trainType":"Steam Locomotive","vibeCheck":"Very Cool Train"}},"type":"trainNode","measured":{"width":242,"height":198},"selected":false,"dragging":false},{"id":"DE","position":{"x":26.90204788216988,"y":2318.30968861718},"data":{"id":"DE","nodeType":"countryNode","country":{"flags":{"png":"https://flagcdn.com/w320/de.png","svg":"https://flagcdn.com/de.svg","alt":"The flag of Germany is composed of three equal horizontal bands of black, red and gold."},"name":{"common":"Germany","official":"Federal Republic of Germany","nativeName":{"deu":{"official":"Bundesrepublik Deutschland","common":"Deutschland"}}},"cca2":"DE"}},"type":"countryNode","measured":{"width":306,"height":52},"selected":false,"dragging":false}],"edges":[{"source":"GE","target":"30617d7b-7dbe-4260-8f1d-eafb71d4a48b","animated":true,"id":"xy-edge__GE-30617d7b-7dbe-4260-8f1d-eafb71d4a48b"},{"source":"GE","target":"aa9db8b1-18b8-4dd4-8975-45f90a0a5a75","animated":true,"id":"xy-edge__GE-aa9db8b1-18b8-4dd4-8975-45f90a0a5a75"},{"source":"30617d7b-7dbe-4260-8f1d-eafb71d4a48b","target":"1cca4fe6-57d9-488a-b4dc-aa6761a4b840","animated":true,"id":"xy-edge__30617d7b-7dbe-4260-8f1d-eafb71d4a48b-1cca4fe6-57d9-488a-b4dc-aa6761a4b840"},{"source":"aa9db8b1-18b8-4dd4-8975-45f90a0a5a75","target":"1cca4fe6-57d9-488a-b4dc-aa6761a4b840","animated":true,"id":"xy-edge__aa9db8b1-18b8-4dd4-8975-45f90a0a5a75-1cca4fe6-57d9-488a-b4dc-aa6761a4b840"},{"source":"1cca4fe6-57d9-488a-b4dc-aa6761a4b840","target":"aafcf9c6-2251-4398-a5ec-50a61dadbb7a","animated":true,"id":"xy-edge__1cca4fe6-57d9-488a-b4dc-aa6761a4b840-aafcf9c6-2251-4398-a5ec-50a61dadbb7a"},{"source":"aafcf9c6-2251-4398-a5ec-50a61dadbb7a","target":"GS","animated":true,"id":"xy-edge__aafcf9c6-2251-4398-a5ec-50a61dadbb7a-GS"},{"source":"GS","target":"d12732ba-834c-4aa4-b0fb-6ae0922358e6","animated":true,"id":"xy-edge__GS-d12732ba-834c-4aa4-b0fb-6ae0922358e6"},{"source":"GS","target":"23779701-3d5b-4157-886b-643f1f1dd1e1","animated":true,"id":"xy-edge__GS-23779701-3d5b-4157-886b-643f1f1dd1e1"},{"source":"GS","target":"bf38712d-1114-4b03-b926-5b0fe36d66e9","animated":true,"id":"xy-edge__GS-bf38712d-1114-4b03-b926-5b0fe36d66e9"},{"source":"bf38712d-1114-4b03-b926-5b0fe36d66e9","target":"DK","animated":true,"id":"xy-edge__bf38712d-1114-4b03-b926-5b0fe36d66e9-DK"},{"source":"DK","target":"46e7aa33-2b96-4bf8-9c72-f4f5295b2e0f","animated":true,"id":"xy-edge__DK-46e7aa33-2b96-4bf8-9c72-f4f5295b2e0f"},{"source":"DK","target":"0ffce9f9-640f-4114-badd-0dbb99e9d939","animated":true,"id":"xy-edge__DK-0ffce9f9-640f-4114-badd-0dbb99e9d939"},{"source":"46e7aa33-2b96-4bf8-9c72-f4f5295b2e0f","target":"b19cd9c6-ec33-439b-95d0-3a6f6c3811aa","animated":true,"id":"xy-edge__46e7aa33-2b96-4bf8-9c72-f4f5295b2e0f-b19cd9c6-ec33-439b-95d0-3a6f6c3811aa"},{"source":"0ffce9f9-640f-4114-badd-0dbb99e9d939","target":"b19cd9c6-ec33-439b-95d0-3a6f6c3811aa","animated":true,"id":"xy-edge__0ffce9f9-640f-4114-badd-0dbb99e9d939-b19cd9c6-ec33-439b-95d0-3a6f6c3811aa"},{"source":"b19cd9c6-ec33-439b-95d0-3a6f6c3811aa","target":"DE","animated":true,"id":"xy-edge__b19cd9c6-ec33-439b-95d0-3a6f6c3811aa-DE"}]}